tartcargo/__init__.py
tartcargo/disko-draw.yml
tartcargo/disko.yml
tartcargo/genesis/__init__.py
tartcargo/genesis/tart-cargo-base.yml
tartcargo/spotless.yml
tartcargo/stimela.conf
tartcargo/tart-download-data.yml
tartcargo/tart-get-archive-data.yml
tartcargo/tart2ms.yml
tartcargo/tartball.yml
tart_cargo-0.3.7.dist-info/METADATA
tart_cargo-0.3.7.dist-info/WHEEL
tart_cargo-0.3.7.dist-info/RECORD
