Metadata-Version: 2.4
Name: tart_cargo
Version: 0.3.7
Summary: Curated cargo of TART radio astronomy packages for stimela 2.0
License: MIT
Author: Tim Molteno
Author-email: tim@elec.ac.nz
Requires-Python: <4.0,>=3.9
Classifier: License :: OSI Approved :: MIT License
Classifier: Programming Language :: Python :: 3
Classifier: Programming Language :: Python :: 3.9
Classifier: Programming Language :: Python :: 3.10
Classifier: Programming Language :: Python :: 3.11
Classifier: Programming Language :: Python :: 3.12
Classifier: Programming Language :: Python :: 3.13
Classifier: Programming Language :: Python :: 3.14
Requires-Dist: requests (>=2.0,<3.0)
Requires-Dist: stimela (>=2.0.1.1,<3.0.0.0)
